fishregression/__init__.py
fishregression/classifier.py
fishregression/cli.py
fishregression/main_classifier.py
fishregression/main_regressor.py
fishregression/pathfinder.py
fishregression/regressor.py
fishregression/data/classifier.pkl
fishregression/data/regressor.pkl
fishregression-0.2.1.dist-info/METADATA
fishregression-0.2.1.dist-info/WHEEL
fishregression-0.2.1.dist-info/entry_points.txt
fishregression-0.2.1.dist-info/top_level.txt
fishregression-0.2.1.dist-info/RECORD
